dmem.v
module dmem(input clk,input [7:0] addr,input we,input [31:0] wdata,input re,output [31:0] rdata);
    reg [31:0] mem [0:255];
    integer i;
    initial begin
        $readmemh("dmem1.hex",mem);
        for (i=0;i<256;i=i+1) if (^mem[i] === 1'bx) mem[i]=0;
    end
    always @(posedge clk) begin
        if (we) mem[addr]<=wdata;
    end
    assign rdata=re?mem[addr]: 32'b0;
endmodule

imem.v
module imem(input [7:0] addr,output [31:0] instr);
reg [31:0] mem [0:255];
initial begin
    $readmemh("imem1.hex",mem);
end
assign instr=mem[addr];
endmodule

mips.v
`timescale 1ns/1ps
module mips(
    input clk,
    input reset
);
reg [31:0] pc;
wire [31:0] pc_plus4=pc + 4;
wire [31:0] instr;
wire [31:0] if_pc=pc;
reg [31:0] IF_ID_instr,IF_ID_pc;
wire [5:0] id_opcode=IF_ID_instr[31:26];
wire [5:0] id_funct=IF_ID_instr[5:0];
wire [4:0] id_rs=IF_ID_instr[25:21];
wire [4:0] id_rt=IF_ID_instr[20:16];
wire [4:0] id_rd=IF_ID_instr[15:11];
wire [15:0] id_imm=IF_ID_instr[15:0];
wire [31:0] id_imm_se={{16{id_imm[15]}}, id_imm};
reg [31:0] regfile [0:31];
wire [31:0] reg_rdata1=regfile[id_rs];
wire [31:0] reg_rdata2=regfile[id_rt];
reg id_regwrite,id_memread,id_memwrite;
reg id_memtoreg,id_alu_src;
reg [2:0] id_alu_ctrl;
always @(*) begin
    id_regwrite=0;
    id_memread=0;
    id_memwrite=0;
    id_memtoreg=0;
    id_alu_src=0;
    id_alu_ctrl=3'b010;
    case(id_opcode)
        6'b000000: begin
            id_regwrite=1;
            if(id_funct==6'b100000)
                id_alu_ctrl=3'b010;
            else if(id_funct==6'b100010)
                id_alu_ctrl=3'b110;
        end
        6'b100011: begin
            id_regwrite=1;
            id_memread=1;
            id_memtoreg=1;
            id_alu_src=1;
        end
        6'b101011: begin
            id_memwrite=1;
            id_alu_src=1;
        end
        6'b001000: begin
            id_regwrite=1;
            id_alu_src=1;
        end
        6'b000100: begin
            id_alu_ctrl=3'b110;
        end
    endcase
end
wire id_branch =!stall&&(id_opcode==6'b000100)&&(reg_rdata1==reg_rdata2);
wire [31:0] branch_target=IF_ID_pc+4+(id_imm_se<<2);
reg [31:0] ID_EX_pc;
reg [31:0] ID_EX_regdata1;
reg [31:0] ID_EX_regdata2;
reg [31:0] ID_EX_imm;
reg [4:0] ID_EX_rs,ID_EX_rt,ID_EX_rd;
reg ID_EX_regwrite,ID_EX_memread;
reg ID_EX_memwrite,ID_EX_memtoreg;
reg ID_EX_alu_src;
reg [2:0] ID_EX_alu_ctrl;
reg [31:0] EX_MEM_aluout;
reg [31:0] EX_MEM_regdata2;
reg [4:0] EX_MEM_rd;
reg EX_MEM_regwrite,EX_MEM_memread;
reg EX_MEM_memwrite,EX_MEM_memtoreg;
reg [31:0] MEM_WB_memdata;
reg [31:0] MEM_WB_aluout;
reg [4:0] MEM_WB_rd;
reg MEM_WB_regwrite,MEM_WB_memtoreg;
reg [31:0] cycle_count;
reg [31:0] instr_count;
reg [31:0] stall_count;
reg [31:0] branch_count;
reg [31:0] clock_gated_cycles;
wire stall;
wire load_use_stall;
assign load_use_stall=ID_EX_memread&&(ID_EX_rt != 0)&&((ID_EX_rt== id_rs)||(ID_EX_rt ==id_rt));
wire branch_stall;
assign branch_stall=(id_opcode==6'b000100)&&((ID_EX_regwrite&&(ID_EX_rd != 0)&&((ID_EX_rd==id_rs)||(ID_EX_rd==id_rt)))||(EX_MEM_regwrite&&(EX_MEM_rd!=0)&&((EX_MEM_rd== id_rs)||(EX_MEM_rd ==id_rt)))||(MEM_WB_regwrite&&(MEM_WB_rd!=0)&&((MEM_WB_rd==id_rs)||(MEM_WB_rd==id_rt))));
assign stall = load_use_stall || branch_stall;
reg [1:0] forwardA,forwardB;
wire dmem_we;
wire dmem_re;
wire [31:0] dmem_addr;
wire [31:0] dmem_wdata;
wire [31:0] dmem_rdata;
wire [31:0] alu_op1;
wire [31:0] alu_op2_reg;
wire [31:0] alu_op2;
wire [31:0] alu_from_EXMEM;
wire [31:0] alu_from_MEMWB;
reg [31:0] EX_ALU_out;
wire if_id_clk_enable;
wire id_ex_clk_enable;
wire regfile_clk_enable;
assign if_id_clk_enable=!stall&&!id_branch;
assign id_ex_clk_enable=!stall&&!id_branch;
reg if_id_clk_en_latch;
reg id_ex_clk_en_latch;
reg regfile_clk_en_latch;
assign regfile_clk_enable=MEM_WB_regwrite && (MEM_WB_rd != 0);
always @(*) begin
    if (!clk) begin
        if_id_clk_en_latch=if_id_clk_enable;
        id_ex_clk_en_latch=id_ex_clk_enable;
	regfile_clk_en_latch=regfile_clk_enable;
    end
end
wire regfile_gated_clk=clk&regfile_clk_en_latch;
wire if_id_gated_clk=clk&if_id_clk_en_latch;
wire id_ex_gated_clk=clk&id_ex_clk_en_latch;
imem imem_inst(
    .addr(pc[9:2]),
    .instr(instr)
);
dmem dmem_inst(
    .clk(clk),
    .addr(dmem_addr[9:2]),
    .we(dmem_we),
    .wdata(dmem_wdata),
    .re(dmem_re),
    .rdata(dmem_rdata)
);
assign dmem_we=EX_MEM_memwrite;
assign dmem_re=EX_MEM_memread;
assign dmem_addr=EX_MEM_aluout;
assign dmem_wdata=EX_MEM_regdata2;
assign alu_from_EXMEM=EX_MEM_aluout;
assign alu_from_MEMWB=
    MEM_WB_memtoreg ?
    MEM_WB_memdata :
    MEM_WB_aluout;
assign alu_op1 =
    (forwardA == 2'b00) ? ID_EX_regdata1 :
    (forwardA == 2'b10) ? alu_from_EXMEM :
                          alu_from_MEMWB;
assign alu_op2_reg =
    (forwardB == 2'b00) ? ID_EX_regdata2 :
    (forwardB == 2'b10) ? alu_from_EXMEM :
                          alu_from_MEMWB;
assign alu_op2 =
    ID_EX_alu_src ?
    ID_EX_imm :
    alu_op2_reg;
integer i;
always @(posedge clk or posedge reset) begin
    if(reset) begin
        pc<=0;
        IF_ID_instr <= 0;
        IF_ID_pc <= 0;
        ID_EX_pc <= 0;
        ID_EX_regdata1 <= 0;
        ID_EX_regdata2 <= 0;
        ID_EX_imm <= 0;
        ID_EX_rs <= 0;
        ID_EX_rt <= 0;
        ID_EX_rd <= 0;
        ID_EX_regwrite <= 0;
        ID_EX_memread <= 0;
        ID_EX_memwrite <= 0;
        ID_EX_memtoreg <= 0;
        ID_EX_alu_src <= 0;
        ID_EX_alu_ctrl <= 0;
        EX_MEM_aluout <= 0;
        EX_MEM_regdata2 <= 0;
        EX_MEM_rd <= 0;
        EX_MEM_regwrite <= 0;
        EX_MEM_memread <= 0;
        EX_MEM_memwrite <= 0;
        EX_MEM_memtoreg <= 0;
        MEM_WB_memdata <= 0;
        MEM_WB_aluout <= 0;
        MEM_WB_rd <= 0;
        MEM_WB_regwrite <= 0;
        MEM_WB_memtoreg <= 0;
        cycle_count <= 0;
        instr_count <= 0;
        stall_count <= 0;
        branch_count <= 0;
        clock_gated_cycles <= 0;
        for(i=0;i<32;i=i+1)
            regfile[i] <= 0;
    end else begin
        cycle_count<=cycle_count + 1;
        if(!stall&&!id_branch&&(IF_ID_instr!=32'h00000000))
            instr_count<=instr_count+1;
        if(stall)
            stall_count<=stall_count+1;
        if(id_branch)
            branch_count<=branch_count+1;
        if(!if_id_clk_enable||!id_ex_clk_enable||!regfile_clk_enable)
            clock_gated_cycles<=clock_gated_cycles+1;
        MEM_WB_memdata <= dmem_rdata;
        MEM_WB_aluout <= EX_MEM_aluout;
        MEM_WB_rd <= EX_MEM_rd;
        MEM_WB_regwrite <= EX_MEM_regwrite;
        MEM_WB_memtoreg <= EX_MEM_memtoreg;
        EX_MEM_aluout <= EX_ALU_out;
        EX_MEM_regdata2 <= alu_op2_reg;
        EX_MEM_rd <= ID_EX_rd;
        EX_MEM_regwrite <= ID_EX_regwrite;
        EX_MEM_memread <= ID_EX_memread;
        EX_MEM_memwrite <= ID_EX_memwrite;
        EX_MEM_memtoreg <= ID_EX_memtoreg;
        if(id_branch) begin
            pc <= branch_target;
            IF_ID_instr <= 0;
            IF_ID_pc <= 0;
            ID_EX_pc <= 0;
            ID_EX_regdata1 <= 0;
            ID_EX_regdata2 <= 0;
            ID_EX_imm <= 0;
            ID_EX_rs <= 0;
            ID_EX_rt <= 0;
            ID_EX_rd <= 0;
            ID_EX_regwrite <= 0;
            ID_EX_memread <= 0;
            ID_EX_memwrite <= 0;
            ID_EX_memtoreg <= 0;
            ID_EX_alu_src <= 0;
            ID_EX_alu_ctrl <= 0;
        end else if(stall) begin
            pc <= pc;
            IF_ID_instr <= IF_ID_instr;
            IF_ID_pc <= IF_ID_pc;
            ID_EX_pc <= 0;
            ID_EX_regdata1 <= 0;
            ID_EX_regdata2 <= 0;
            ID_EX_imm <= 0;
            ID_EX_rs <= 0;
            ID_EX_rt <= 0;
            ID_EX_rd <= 0;
            ID_EX_regwrite <= 0;
            ID_EX_memread <= 0;
            ID_EX_memwrite <= 0;
            ID_EX_memtoreg <= 0;
            ID_EX_alu_src <= 0;
            ID_EX_alu_ctrl <= 0;
        end else begin
            pc <= pc_plus4;
            IF_ID_instr <= instr;
            IF_ID_pc <= if_pc;
            ID_EX_pc <= IF_ID_pc;
            ID_EX_regdata1 <= reg_rdata1;
            ID_EX_regdata2 <= reg_rdata2;
            ID_EX_imm <= id_imm_se;
            ID_EX_rs <= id_rs;
            ID_EX_rt <= id_rt;
            ID_EX_rd <=
                (id_opcode == 6'b000000) ?
                id_rd :
                id_rt;
            ID_EX_regwrite <= id_regwrite;
            ID_EX_memread <= id_memread;
            ID_EX_memwrite <= id_memwrite;
            ID_EX_memtoreg <= id_memtoreg;
            ID_EX_alu_src <= id_alu_src;
            ID_EX_alu_ctrl <= id_alu_ctrl;
        end
    end
end
always @(posedge regfile_gated_clk or posedge reset) begin
    if(reset) begin
        for(i=0;i<32;i=i+1)
            regfile[i]<=0;
    end else begin
        if(MEM_WB_regwrite&&(MEM_WB_rd!=0))
            regfile[MEM_WB_rd]<=(MEM_WB_memtoreg ?MEM_WB_memdata:MEM_WB_aluout);
    end
end
always @(*) begin
    forwardA=2'b00;
    forwardB=2'b00;
    if(EX_MEM_regwrite &&(EX_MEM_rd != 0) &&(EX_MEM_rd == ID_EX_rs))
        forwardA = 2'b10;
    if(EX_MEM_regwrite&&(EX_MEM_rd!=0)&&(EX_MEM_rd==ID_EX_rt))
        forwardB=2'b10;
    if(MEM_WB_regwrite&&(MEM_WB_rd!=0)&&(MEM_WB_rd==ID_EX_rs)&&!(EX_MEM_regwrite&&(EX_MEM_rd!=0)&&(EX_MEM_rd==ID_EX_rs)))
        forwardA=2'b01;
    if(MEM_WB_regwrite&&(MEM_WB_rd!=0)&&(MEM_WB_rd==ID_EX_rt) &&!(EX_MEM_regwrite&&(EX_MEM_rd!=0)&&(EX_MEM_rd==ID_EX_rt)))
        forwardB=2'b01;
end
always @(*) begin
    case(ID_EX_alu_ctrl)
        3'b010:
            EX_ALU_out=alu_op1+alu_op2;
        3'b110:
            EX_ALU_out=alu_op1-alu_op2;
        default:
            EX_ALU_out=alu_op1+alu_op2;
    endcase
end
endmodule

tb.v
`timescale 1ns/1ps
module tb;
reg clk, reset;
mips cpu(
    .clk(clk),
    .reset(reset)
);
initial clk=0;
always #5 clk=~clk;
integer cycle;
initial begin
    $dumpfile("mips.vcd");
    $dumpvars(0,tb);
    reset=1;
    #20;
    reset=0;
    for(cycle=0;cycle<45;cycle=cycle+1) begin
        @(posedge clk);
        #1;
        $display("cycle=%0d pc=%0d branches=%0d stalls=%0d instr=%0d",cpu.cycle_count,cpu.pc,cpu.branch_count,cpu.stall_count,cpu.instr_count);
    end
    $display("$at=%0d",cpu.regfile[1]);
    $display("$v0=%0d",cpu.regfile[2]);
    $display("$v1=%0d",cpu.regfile[3]);
    $display("$a0=%0d",cpu.regfile[4]);
    $display("$a1=%0d",cpu.regfile[5]);
    $display("$a2=%0d",cpu.regfile[6]);
    $display("$a3=%0d",cpu.regfile[7]);
    $display("$t0=%0d",cpu.regfile[8]);
    $display("$t1=%0d",cpu.regfile[9]);
    $display("$t2=%0d",cpu.regfile[10]);
    $display("$t3=%0d",cpu.regfile[11]);
    $display("$t4=%0d",cpu.regfile[12]);
    $display("$t5=%0d",cpu.regfile[13]);
    $display("$t6=%0d",cpu.regfile[14]);
    $display("$t7=%0d",cpu.regfile[15]);
    $display("$t8=%0d",cpu.regfile[24]);
    $finish;
end
endmodule

mips.vcd
$date
	Wed May 20 12:53:15 2026
$end
$version
	Icarus Verilog
$end
$timescale
	1ps
$end
$scope module tb $end
$var reg 1 ! clk $end
$var reg 1 " reset $end
$var integer 32 # cycle [31:0] $end
$scope module cpu $end
$var wire 32 $ alu_from_EXMEM [31:0] $end
$var wire 1 % branch_stall $end
$var wire 1 ! clk $end
$var wire 32 & dmem_addr [31:0] $end
$var wire 1 ' dmem_re $end
$var wire 32 ( dmem_wdata [31:0] $end
$var wire 1 ) dmem_we $end
$var wire 1 * id_branch $end
$var wire 1 + id_ex_clk_enable $end
$var wire 1 , id_ex_gated_clk $end
$var wire 1 - if_id_clk_enable $end
$var wire 1 . if_id_gated_clk $end
$var wire 32 / if_pc [31:0] $end
$var wire 1 0 load_use_stall $end
$var wire 32 1 reg_rdata1 [31:0] $end
$var wire 32 2 reg_rdata2 [31:0] $end
$var wire 1 3 regfile_clk_enable $end
$var wire 1 4 regfile_gated_clk $end
$var wire 1 " reset $end
$var wire 1 5 stall $end
$var wire 32 6 pc_plus4 [31:0] $end
$var wire 32 7 instr [31:0] $end
$var wire 5 8 id_rt [4:0] $end
$var wire 5 9 id_rs [4:0] $end
$var wire 5 : id_rd [4:0] $end
$var wire 6 ; id_opcode [5:0] $end
$var wire 32 < id_imm_se [31:0] $end
$var wire 16 = id_imm [15:0] $end
$var wire 6 > id_funct [5:0] $end
$var wire 32 ? dmem_rdata [31:0] $end
$var wire 32 @ branch_target [31:0] $end
$var wire 32 A alu_op2_reg [31:0] $end
$var wire 32 B alu_op2 [31:0] $end
$var wire 32 C alu_op1 [31:0] $end
$var wire 32 D alu_from_MEMWB [31:0] $end
$var reg 32 E EX_ALU_out [31:0] $end
$var reg 32 F EX_MEM_aluout [31:0] $end
$var reg 1 ' EX_MEM_memread $end
$var reg 1 G EX_MEM_memtoreg $end
$var reg 1 H EX_MEM_memwrite $end
$var reg 5 I EX_MEM_rd [4:0] $end
$var reg 32 J EX_MEM_regdata2 [31:0] $end
$var reg 1 K EX_MEM_regwrite $end
$var reg 3 L ID_EX_alu_ctrl [2:0] $end
$var reg 1 M ID_EX_alu_src $end
$var reg 32 N ID_EX_imm [31:0] $end
$var reg 1 O ID_EX_memread $end
$var reg 1 P ID_EX_memtoreg $end
$var reg 1 Q ID_EX_memwrite $end
$var reg 32 R ID_EX_pc [31:0] $end
$var reg 5 S ID_EX_rd [4:0] $end
$var reg 32 T ID_EX_regdata1 [31:0] $end
$var reg 32 U ID_EX_regdata2 [31:0] $end
$var reg 1 V ID_EX_regwrite $end
$var reg 5 W ID_EX_rs [4:0] $end
$var reg 5 X ID_EX_rt [4:0] $end
$var reg 32 Y IF_ID_instr [31:0] $end
$var reg 32 Z IF_ID_pc [31:0] $end
$var reg 32 [ MEM_WB_aluout [31:0] $end
$var reg 32 \ MEM_WB_memdata [31:0] $end
$var reg 1 ] MEM_WB_memtoreg $end
$var reg 5 ^ MEM_WB_rd [4:0] $end
$var reg 1 _ MEM_WB_regwrite $end
$var reg 32 ` branch_count [31:0] $end
$var reg 32 a clock_gated_cycles [31:0] $end
$var reg 32 b cycle_count [31:0] $end
$var reg 2 c forwardA [1:0] $end
$var reg 2 d forwardB [1:0] $end
$var reg 3 e id_alu_ctrl [2:0] $end
$var reg 1 f id_alu_src $end
$var reg 1 g id_ex_clk_en_latch $end
$var reg 1 h id_memread $end
$var reg 1 i id_memtoreg $end
$var reg 1 j id_memwrite $end
$var reg 1 k id_regwrite $end
$var reg 1 l if_id_clk_en_latch $end
$var reg 32 m instr_count [31:0] $end
$var reg 32 n pc [31:0] $end
$var reg 1 o regfile_clk_en_latch $end
$var reg 32 p stall_count [31:0] $end
$var integer 32 q i [31:0] $end
$scope module dmem_inst $end
$var wire 8 r addr [7:0] $end
$var wire 1 ! clk $end
$var wire 1 ' re $end
$var wire 32 s wdata [31:0] $end
$var wire 1 ) we $end
$var wire 32 t rdata [31:0] $end
$var integer 32 u i [31:0] $end
$upscope $end
$scope module imem_inst $end
$var wire 8 v addr [7:0] $end
$var wire 32 w instr [31:0] $end
$upscope $end
$upscope $end
$upscope $end
$enddefinitions $end
$comment Show the parameter values. $end
$dumpall
$end
#0
$dumpvars
b100000000010000000000000000101 w
b0 v
b100000000 u
b0 t
b0 s
b0 r
b100000 q
b0 p
0o
b0 n
b0 m
1l
1k
0j
0i
0h
1g
0f
b10 e
b0 d
b0 c
b0 b
b0 a
b0 `
0_
b0 ^
0]
b0 \
b0 [
b0 Z
b0 Y
b0 X
b0 W
0V
b0 U
b0 T
b0 S
b0 R
0Q
0P
0O
b0 N
0M
b0 L
0K
b0 J
b0 I
0H
0G
b0 F
b0 E
b0 D
b0 C
b0 B
b0 A
b100 @
b0 ?
b0 >
b0 =
b0 <
b0 ;
b0 :
b0 9
b0 8
b100000000010000000000000000101 7
b100 6
05
04
03
b0 2
b0 1
00
b0 /
0.
1-
0,
1+
0*
0)
b0 (
0'
b0 &
0%
b0 $
bx #
1"
0!
$end
#5000
1.
1,
b100000 q
1!
#10000
0.
0,
0!
#15000
1.
1,
b100000 q
1!
#20000
0.
0,
0!
b0 #
0"
#25000
1f
1k
b11000 @
b1000 ;
b101 >
b1000 8
b101 <
b101 =
b100000000010010000000000001010 7
b100000000010010000000000001010 w
b1 v
b10 L
1V
b100000000010000000000000000101 Y
b1000 6
b100 /
b100 n
b1 a
b1 b
1.
1,
1!
#26000
b1 #
#30000
0.
0,
0!
#35000
b101 E
1f
1k
b101 B
b1010 >
b1001 8
b1010 <
b1010 =
b1000010010101000000100000 7
b1000010010101000000100000 w
b10 v
1M
b1000 S
b1000 X
b101 N
b110000 @
b100 Z
b100000000010010000000000001010 Y
b1100 6
b1000 /
b1000 n
1K
b10 a
b1 m
b10 b
1.
1,
1!
#36000
b10 #
#40000
0.
0,
0!
#45000
b1010 E
0f
1k
b1010 B
b0 ;
b100000 >
b1000 9
b1010 :
b101000000100000 <
b101000000100000 =
b1010010000101100000100000 7
b1010010000101100000100000 w
b11 v
b1 r
b1001 S
b1001 X
b1010 N
b100 R
b10100000010001100 @
b1000 Z
b1000010010101000000100000 Y
b10000 6
b1100 /
b1100 n
b1000 I
b101 $
b101 &
b101 F
1_
b11 a
b10 m
b11 b
1.
1,
1!
#46000
b11 #
#50000
0.
0,
0!
#55000
b1111 E
b101 C
b1010 A
b1010 B
b1010 9
b1000 8
b1011 :
b101100000100000 <
b101100000100000 =
b10001100000011000000000000000000 7
b10001100000011000000000000000000 w
b100 v
b10 r
b1 c
b10 d
13
b101 D
0M
b1010 S
b1000 W
b101000000100000 N
b1000 R
b10110000010010000 @
b1100 Z
b1010010000101100000100000 Y
b10100 6
b10000 /
b10000 n
b1001 I
b1010 $
b1010 &
b1010 F
b1000 ^
b101 [
b100 a
b11 m
b100 b
1.
1,
1!
#56000
b100 #
#60000
0.
0,
1o
0!
#65000
b0 B
b1111 E
1f
1i
1h
1k
b0 A
b1111 C
b100011 ;
b0 >
b0 9
b1100 8
b0 :
b0 <
b0 =
b1100010010110100000100000 7
b1100010010110100000100000 w
b101 v
b11 r
b0 d
b10 c
b1010 D
b0 2
b1011 S
b1000 X
b1010 W
b101100000100000 N
b1100 R
b10100 @
b10000 Z
b10001100000011000000000000000000 Y
b11000 6
b10100 /
b10100 n
b1010 I
b1010 (
b1010 s
b1010 J
b1111 $
b1111 &
b1111 F
b1001 ^
b1010 [
b100 m
b101 b
14
1.
1,
1!
#66000
b101 #
#70000
04
0.
0,
0!
#75000
0-
0+
15
b0 E
10
0f
0i
0h
1k
b0 C
b0 ;
b100000 >
b1100 9
b1010 2
b1001 8
b1101 :
b110100000100000 <
b110100000100000 =
b100000000011100000000000000011 7
b100000000011100000000000000011 w
b110 v
b0 c
b1111 D
1M
1P
1O
b1100 S
b1100 X
b0 W
b0 N
b10000 R
b11010000010011000 @
b10100 Z
b1100010010110100000100000 Y
b11100 6
b11000 /
b11000 n
b1011 I
b0 (
b0 s
b0 J
b1010 ^
b1111 [
b101 m
b110 b
14
1.
1,
1!
#76000
b110 #
#80000
04
0.
0,
0g
0l
0!
#85000
1-
1+
05
00
b10100 ?
b10100 t
b0 r
b0 L
0M
0P
0O
0V
b0 S
b0 X
b0 R
1G
1'
b1100 I
b0 $
b0 &
b0 F
b1011 ^
b101 a
b1 p
b111 b
14
1!
#86000
b111 #
#90000
04
1g
1l
0!
#95000
b11110 E
b1010 B
1f
1k
b10100 C
b1010 A
b1000 ;
b11 >
b0 9
b0 2
b1110 8
b0 :
b11 <
b11 =
b100000000011110000000000000100 7
b100000000011110000000000000100 w
b111 v
b0 ?
b0 t
b1 c
b10100 D
b10 L
1V
b1101 S
b1001 X
b1100 W
b110100000100000 N
b1010 U
b10100 R
b101000 @
b11000 Z
b100000000011100000000000000011 Y
b100000 6
b11100 /
b11100 n
0G
0'
0K
b0 I
1]
b1100 ^
b0 [
b10100 \
b110 m
b1000 b
14
1.
1,
1!
#96000
b1000 #
#100000
04
0.
0,
0!
#105000
b11 E
1f
1k
b0 C
b11 B
b0 A
b100 >
b1111 8
b100 <
b100 =
b10001110011110000000000000001 7
b10001110011110000000000000001 w
b1000 v
b111 r
b0 c
03
b0 D
1M
b1110 S
b1110 X
b0 W
b11 N
b0 U
b11000 R
b110000 @
b11100 Z
b100000000011110000000000000100 Y
b100100 6
b100000 /
b100000 n
1K
b1101 I
b1010 (
b1010 s
b1010 J
b11110 $
b11110 &
b11110 F
0]
0_
b0 ^
b0 \
b111 m
b1001 b
14
1.
1,
1!
#106000
b1001 #
#110000
04
0.
0,
0o
0!
#115000
15
1%
0-
0+
0*
b100 E
b110 e
0f
0k
b100 B
b100 ;
b1 >
b1110 9
b1 <
b1 =
b100000000110000000000000000001 7
b100000000110000000000000000001 w
b1001 v
b0 r
13
b11110 D
b1111 S
b1111 X
b100 N
b11100 R
b101000 @
b100000 Z
b10001110011110000000000000001 Y
b101000 6
b100100 /
b100100 n
b1110 I
b0 (
b0 s
b0 J
b11 $
b11 &
b11 F
1_
b1101 ^
b11110 [
b110 a
b1000 m
b1010 b
1.
1,
1!
#116000
b1010 #
#120000
0.
0,
1o
0g
0l
0!
#125000
b0 E
b0 B
b1 r
b11 D
b0 L
0M
0V
b0 S
b0 X
b0 N
b0 R
b1111 I
b100 $
b100 &
b100 F
b1110 ^
b11 [
b111 a
b10 p
b1011 b
14
1!
#126000
b1011 #
#130000
04
0!
#135000
b0 r
b100 D
b11 1
0K
b0 I
b0 $
b0 &
b0 F
b1111 ^
b100 [
b1000 a
b11 p
b1100 b
14
1!
#136000
b1100 #
#140000
04
0!
#145000
1-
1+
05
0%
03
b0 D
b100 2
0_
b0 ^
b0 [
b1001 a
b100 p
b1101 b
14
1!
#146000
b1101 #
#150000
04
0o
1g
1l
0!
#155000
1-
1+
b100 B
1f
1k
b10 e
0*
b11111111111111111111111111111111 E
b100 A
b11 C
b1000 ;
b0 1
b0 9
b0 2
b11000 8
b100000000000100000000000000010 7
b100000000000100000000000000010 w
b1010 v
b110 L
b1111 S
b1111 X
b1110 W
b1 N
b100 U
b11 T
b100000 R
b101100 @
b100100 Z
b100000000110000000000000000001 Y
b101100 6
b101000 /
b101000 n
b1010 a
b1001 m
b1110 b
1.
1,
1!
#156000
b1110 #
#160000
0.
0,
0!
#165000
1f
1k
b1 E
b1 B
b0 A
b0 C
b10 >
b10 8
b10 <
b10 =
b0 7
b0 w
b1011 v
b11111111 r
b10 L
1M
1V
b11000 S
b11000 X
b0 W
b0 U
b0 T
b100100 R
b110100 @
b101000 Z
b100000000000100000000000000010 Y
b110000 6
b101100 /
b101100 n
b1111 I
b100 (
b100 s
b100 J
b11111111111111111111111111111111 $
b11111111111111111111111111111111 &
b11111111111111111111111111111111 F
b1011 a
b1010 m
b1111 b
1.
1,
1!
#166000
b1111 #
#170000
0.
0,
0!
#175000
b10 E
0f
1k
b10 B
b0 ;
b0 >
b0 8
b0 <
b0 =
bx 7
bx w
b1100 v
b0 r
b11111111111111111111111111111111 D
b10 S
b10 X
b10 N
b101000 R
b110000 @
b101100 Z
b0 Y
b110100 6
b110000 /
b110000 n
1K
b11000 I
b0 (
b0 s
b0 J
b1 $
b1 &
b1 F
b1111 ^
b11111111111111111111111111111111 [
b1100 a
b1011 m
b10000 b
1.
1,
1!
#176000
b10000 #
#180000
0.
0,
0!
#185000
x5
x%
x-
x+
x*
b0 E
0k
b0 B
bx ;
bx >
bx 1
bx 9
bx 2
bx 8
bx :
bx <
bx =
b1101 v
13
b1 D
0M
b0 S
b0 X
b0 N
b101100 R
bx @
b110000 Z
bx Y
b111000 6
b110100 /
b110100 n
b10 I
b10 $
b10 &
b10 F
1_
b11000 ^
b1 [
b1101 a
b10001 b
1.
1,
1!
#186000
b10001 #
#190000
0.
0,
1o
xg
xl
0!
#195000
bx B
bx E
bx A
bx C
b1110 v
b10 D
0V
bx S
bx X
bx W
bx N
bx U
bx T
b110000 R
b110100 Z
b111100 6
b111000 /
b111000 n
b0 I
b0 $
b0 &
b0 F
b10 ^
b10 [
b10010 b
14
x.
x,
1!
#196000
b10010 #
#200000
04
0.
0,
0!
#205000
05
0%
b1111 v
bx r
03
b0 D
b110100 R
b111000 Z
b1000000 6
b111100 /
b111100 n
0K
bx I
bx (
bx s
bx J
bx $
bx &
bx F
b0 ^
b0 [
b10011 b
14
x.
x,
1!
#206000
b10011 #
#210000
04
0.
0,
0o
0!
#215000
b10000 v
bx D
b111000 R
b111100 Z
b1000100 6
b1000000 /
b1000000 n
0_
bx ^
bx [
b1110 a
b10100 b
x.
x,
1!
#216000
b10100 #
#220000
0.
0,
0!
#225000
b10001 v
b111100 R
b1000000 Z
b1001000 6
b1000100 /
b1000100 n
b1111 a
b10101 b
x.
x,
1!
#226000
b10101 #
#230000
0.
0,
0!
#235000
b10010 v
b1000000 R
b1000100 Z
b1001100 6
b1001000 /
b1001000 n
b10000 a
b10110 b
x.
x,
1!
#236000
b10110 #
#240000
0.
0,
0!
#245000
b10011 v
b1000100 R
b1001000 Z
b1010000 6
b1001100 /
b1001100 n
b10001 a
b10111 b
x.
x,
1!
#246000
b10111 #
#250000
0.
0,
0!
#255000
b10100 v
b1001000 R
b1001100 Z
b1010100 6
b1010000 /
b1010000 n
b10010 a
b11000 b
x.
x,
1!
#256000
b11000 #
#260000
0.
0,
0!
#265000
b10101 v
b1001100 R
b1010000 Z
b1011000 6
b1010100 /
b1010100 n
b10011 a
b11001 b
x.
x,
1!
#266000
b11001 #
#270000
0.
0,
0!
#275000
b10110 v
b1010000 R
b1010100 Z
b1011100 6
b1011000 /
b1011000 n
b10100 a
b11010 b
x.
x,
1!
#276000
b11010 #
#280000
0.
0,
0!
#285000
b10111 v
b1010100 R
b1011000 Z
b1100000 6
b1011100 /
b1011100 n
b10101 a
b11011 b
x.
x,
1!
#286000
b11011 #
#290000
0.
0,
0!
#295000
b11000 v
b1011000 R
b1011100 Z
b1100100 6
b1100000 /
b1100000 n
b10110 a
b11100 b
x.
x,
1!
#296000
b11100 #
#300000
0.
0,
0!
#305000
b11001 v
b1011100 R
b1100000 Z
b1101000 6
b1100100 /
b1100100 n
b10111 a
b11101 b
x.
x,
1!
#306000
b11101 #
#310000
0.
0,
0!
#315000
b11010 v
b1100000 R
b1100100 Z
b1101100 6
b1101000 /
b1101000 n
b11000 a
b11110 b
x.
x,
1!
#316000
b11110 #
#320000
0.
0,
0!
#325000
b11011 v
b1100100 R
b1101000 Z
b1110000 6
b1101100 /
b1101100 n
b11001 a
b11111 b
x.
x,
1!
#326000
b11111 #
#330000
0.
0,
0!
#335000
b11100 v
b1101000 R
b1101100 Z
b1110100 6
b1110000 /
b1110000 n
b11010 a
b100000 b
x.
x,
1!
#336000
b100000 #
#340000
0.
0,
0!
#345000
b11101 v
b1101100 R
b1110000 Z
b1111000 6
b1110100 /
b1110100 n
b11011 a
b100001 b
x.
x,
1!
#346000
b100001 #
#350000
0.
0,
0!
#355000
b11110 v
b1110000 R
b1110100 Z
b1111100 6
b1111000 /
b1111000 n
b11100 a
b100010 b
x.
x,
1!
#356000
b100010 #
#360000
0.
0,
0!
#365000
b11111 v
b1110100 R
b1111000 Z
b10000000 6
b1111100 /
b1111100 n
b11101 a
b100011 b
x.
x,
1!
#366000
b100011 #
#370000
0.
0,
0!
#375000
b100000 v
b1111000 R
b1111100 Z
b10000100 6
b10000000 /
b10000000 n
b11110 a
b100100 b
x.
x,
1!
#376000
b100100 #
#380000
0.
0,
0!
#385000
b100001 v
b1111100 R
b10000000 Z
b10001000 6
b10000100 /
b10000100 n
b11111 a
b100101 b
x.
x,
1!
#386000
b100101 #
#390000
0.
0,
0!
#395000
b100010 v
b10000000 R
b10000100 Z
b10001100 6
b10001000 /
b10001000 n
b100000 a
b100110 b
x.
x,
1!
#396000
b100110 #
#400000
0.
0,
0!
#405000
b100011 v
b10000100 R
b10001000 Z
b10010000 6
b10001100 /
b10001100 n
b100001 a
b100111 b
x.
x,
1!
#406000
b100111 #
#410000
0.
0,
0!
#415000
b100100 v
b10001000 R
b10001100 Z
b10010100 6
b10010000 /
b10010000 n
b100010 a
b101000 b
x.
x,
1!
#416000
b101000 #
#420000
0.
0,
0!
